json_logger_stdout/__init__.py
json_logger_stdout/json_logger_stdout.py
json_logger_stdout-1.2.6.dist-info/METADATA
json_logger_stdout-1.2.6.dist-info/WHEEL
json_logger_stdout-1.2.6.dist-info/RECORD
