Metadata-Version: 2.1
Name: json-logger-stdout
Version: 1.2.6
Summary: JSON Logger for MicroServices. Prints logs to the stdout of the service and can be shipped to ES by leveraging a centralized tool like Fluentd.
Home-page: https://gitlab.com/chalukyaj/json-logger-stdout
License: MIT
Keywords: json-logger,micro-services,containers,docker,kubernetes,fluetd,stdout
Author: Chalukya J
Author-email: chalukyaj@gmail.com
Requires-Python: >=3.6,<4.0
Classifier: License :: OSI Approved :: MIT License
Classifier: Operating System :: OS Independent
Classifier: Programming Language :: Python :: 3
Classifier: Programming Language :: Python :: 3.6
Classifier: Programming Language :: Python :: 3.7
Classifier: Programming Language :: Python :: 3.8
Classifier: Programming Language :: Python :: 3.9
Classifier: Programming Language :: Python :: 3.10
Classifier: Programming Language :: Python :: 3.11
Classifier: Programming Language :: Python :: 3.12
Classifier: Topic :: Software Development :: Libraries :: Python Modules
Classifier: Topic :: System :: Distributed Computing
Classifier: Topic :: System :: Logging
Classifier: Topic :: Terminals :: Serial
Requires-Dist: python-json-logger (>=2.0.2,<3.0.0)
Project-URL: Repository, https://gitlab.com/chalukyaj/json-logger-stdout
